LICENSE
README.md
setup.py
tundra_xaxlib/TundraXaxlibConstants.py
tundra_xaxlib/__init__.py
tundra_xaxlib/etc/UninstantiableClassMixin.py
tundra_xaxlib/etc/__init__.py
tundra_xaxlib/exc/InvalidMessageDataExc.py
tundra_xaxlib/exc/InvalidWireformatMessageDataExc.py
tundra_xaxlib/exc/TundraXaxlibBaseExc.py
tundra_xaxlib/exc/__init__.py
tundra_xaxlib/v1/ErroneousResponseMessage.py
tundra_xaxlib/v1/MessageType.py
tundra_xaxlib/v1/RequestMessage.py
tundra_xaxlib/v1/SuccessfulResponseMessage.py
tundra_xaxlib/v1/V1Constants.py
tundra_xaxlib/v1/WireformatParsingHelpers.py
tundra_xaxlib/v1/WireformattableIface.py
tundra_xaxlib/v1/_InternalV1Constants.py
tundra_xaxlib/v1/_MiscHelpers.py
tundra_xaxlib/v1/_ValidationHelpers.py
tundra_xaxlib/v1/_WireformatHelpers.py
tundra_xaxlib/v1/__init__.py
tundra_xaxlib_python.egg-info/PKG-INFO
tundra_xaxlib_python.egg-info/SOURCES.txt
tundra_xaxlib_python.egg-info/dependency_links.txt
tundra_xaxlib_python.egg-info/top_level.txt