Metadata-Version: 2.1
Name: tundra-xaxlib-python
Version: 1.0.2
Summary: Tundra-NAT64 external address translation library for Python
Home-page: https://github.com/vitlabuda/tundra-xaxlib-python
Author: Vít Labuda
Author-email: dev@vitlabuda.cz
License: BSD License
Project-URL: Bug Tracker, https://github.com/vitlabuda/tundra-xaxlib-python/issues
Platform: UNKNOWN
Classifier: Development Status :: 5 - Production/Stable
Classifier: Intended Audience :: Developers
Classifier: License :: OSI Approved :: BSD License
Classifier: Operating System :: OS Independent
Classifier: Programming Language :: Python :: 3
Classifier: Programming Language :: Python :: 3.9
Classifier: Programming Language :: Python :: 3.10
Classifier: Programming Language :: Python :: 3.11
Classifier: Programming Language :: Python :: 3.12
Classifier: Topic :: Software Development :: Libraries
Classifier: Typing :: Typed
Requires-Python: >=3.9
License-File: LICENSE
